MANIFEST.in
README.md
setup.cfg
setup.py
backend/__init__.py
backend/common/__init__.py
backend/common/colors.py
backend/common/constants.py
backend/common/errors.py
backend/common/genesets.py
backend/common/compute/__init__.py
backend/common/compute/diffexp_generic.py
backend/common/fbs/__init__.py
backend/common/fbs/matrix.py
backend/common/fbs/NetEncoding/Column.py
backend/common/fbs/NetEncoding/Float32Array.py
backend/common/fbs/NetEncoding/Float64Array.py
backend/common/fbs/NetEncoding/Int32Array.py
backend/common/fbs/NetEncoding/JSONEncodedArray.py
backend/common/fbs/NetEncoding/Matrix.py
backend/common/fbs/NetEncoding/TypedArray.py
backend/common/fbs/NetEncoding/Uint32Array.py
backend/common/fbs/NetEncoding/__init__.py
backend/common/utils/__init__.py
backend/common/utils/aws_secret_utils.py
backend/common/utils/data_locator.py
backend/common/utils/type_conversion_utils.py
backend/common/utils/utils.py
backend/server/__init__.py
backend/server/__main__.py
backend/server/default_config.py
backend/server/requirements-prepare.txt
backend/server/requirements.txt
backend/server/app/__init__.py
backend/server/app/app.py
backend/server/auth/__init__.py
backend/server/auth/auth.py
backend/server/auth/auth_none.py
backend/server/auth/auth_session.py
backend/server/auth/auth_test.py
backend/server/cli/__init__.py
backend/server/cli/cli.py
backend/server/cli/launch.py
backend/server/cli/prepare.py
backend/server/cli/schema.py
backend/server/cli/upgrade.py
backend/server/common/__init__.py
backend/server/common/corpora.py
backend/server/common/health.py
backend/server/common/rest.py
backend/server/common/annotations/__init__.py
backend/server/common/annotations/annotations.py
backend/server/common/annotations/local_file_csv.py
backend/server/common/config/__init__.py
backend/server/common/config/app_config.py
backend/server/common/config/base_config.py
backend/server/common/config/client_config.py
backend/server/common/config/dataset_config.py
excellxgene.egg-info/PKG-INFO
excellxgene.egg-info/SOURCES.txt
excellxgene.egg-info/dependency_links.txt
excellxgene.egg-info/entry_points.txt
excellxgene.egg-info/not-zip-safe
excellxgene.egg-info/requires.txt
excellxgene.egg-info/top_level.txt