Metadata-Version: 2.1
Name: excellxgene
Version: 2.9.4
Summary: Web application for exploration of large scale scRNA-seq datasets, upgraded to enable end-to-end interactive analysis.
Home-page: https://github.com/czbiohub/excellxgene
Author: Chan Zuckerberg Biohub
Author-email: alexander.tarashansky@czbiohub.org
License: MIT
Platform: UNKNOWN
Classifier: Framework :: Flask
Classifier: Intended Audience :: Science/Research
Classifier: License :: OSI Approved :: MIT License
Classifier: Natural Language :: English
Classifier: Operating System :: POSIX
Classifier: Operating System :: Unix
Classifier: Operating System :: MacOS :: MacOS X
Classifier: Programming Language :: JavaScript
Classifier: Programming Language :: Python :: 3.8
Classifier: Programming Language :: Python :: 3 :: Only
Classifier: Topic :: Scientific/Engineering :: Bio-Informatics
